LICENSE
MANIFEST.in
README.md
pcalg.py
setup.py
pcalg.egg-info/PKG-INFO
pcalg.egg-info/SOURCES.txt
pcalg.egg-info/dependency_links.txt
pcalg.egg-info/requires.txt
pcalg.egg-info/top_level.txt