Metadata-Version: 1.1
Name: pcalg
Version: 0.1.4
Summary: CPDAG Estimation using PC-Algorithm
Home-page: UNKNOWN
Author: Keiichi SHIMA
Author-email: keiichi@iijlab.net
License: BSD License
Platform: UNKNOWN
Classifier: Development Status :: 4 - Beta
Classifier: Environment :: Console
Classifier: Intended Audience :: Information Technology
Classifier: Intended Audience :: Science/Research
Classifier: License :: OSI Approved :: BSD License
Classifier: Programming Language :: Python :: 2.7
Classifier: Topic :: Scientific/Engineering :: Information Analysis
Classifier: Topic :: Software Development :: Libraries :: Python Modules
